kdbx/__init__.py
kdbx-0.0.0.dist-info/METADATA
kdbx-0.0.0.dist-info/WHEEL
kdbx-0.0.0.dist-info/top_level.txt
kdbx-0.0.0.dist-info/RECORD
