Metadata-Version: 2.4
Name: kdbx
Version: 0.0.0
Summary: Coming soon
Author-email: KX <tech@kx.com>
